{"color": {"name": "red", "url": "https://pokeapi.co/api/v2/pokemon-color/8/"}, "evolves_from_species": {"name": "rufflet"}, "generation": "unova", "id": 627, "names": {"ko": "워글", "fr": "Gueriaigle", "de": "Washakwil", "es": "Braviary", "it": "Braviary", "en": "Braviary", "ja": "ウォーグル"}, "descriptions": {"en": "Screaming a bloodcurdling battle cry, this huge and ferocious bird Pokémon goes out on the hunt. It blasts lakes with shock waves, then scoops up any prey that float to the water's surface.", "ja": "血の気が　多く　荒っぽいので ガラルの　運び屋の　座は アーマーガアに　奪われた。", "it": "A causa del suo carattere irruente e violento ha perso il posto di corriere a Galar, che gli è stato rubato da Corviknight.", "es": "Su carácter agresivo e irascible le ha hecho perder su puesto como transportista en Galar en favor de los Corviknight.", "de": "Da es hitzköpfig und aggressiv ist, hat es den Posten als Kurier in Galar an Krarmor verloren.", "fr": "Son caractère agressif et violent lui a valu de perdre son rôle de transporteur à Galar au profit de Corvaillus.", "ko": "혈기왕성하고 거칠어서 가라르의 배달부 자리는 아머까오에게 뺏겼다."}}