{"color": {"name": "black", "url": "https://pokeapi.co/api/v2/pokemon-color/1/"}, "evolves_from_species": null, "generation": "sinnoh", "id": 487, "names": {"ko": "기라티나", "fr": "Giratina", "de": "Giratina", "es": "Giratina", "it": "Giratina", "en": "Giratina", "ja": "ギラティナ"}, "descriptions": {"en": "There is one Hisuian verse that tells of a powerful light creating a deep shadow. I imagine that this deep shadow is Giratina.", "ja": "暴れ者　ゆえ　追い出されたが 破れた世界と　言われる　場所で 静かに　元の世界を　見ていた。", "it": "È stato bandito per la sua violenza. Osserva il vecchio mondo in silenzio dal Mondo Distorto.", "es": "Fue desterrado por su violencia. Observa el mundo en silencio desde el Mundo Distorsión.", "de": "Es wurde aufgrund seines Verhaltens verbannt. Aus der Zerrwelt schaut es auf die alte Welt.", "fr": "Sa grande violence lui a valu d’être banni. Il observe les hommes en silence depuis le Monde Distorsion.", "ko": "난폭하다는 이유로 쫓겨났지만 깨어진 세계라고 전해지는 장소에서 조용히 원래 세계를 보고 있었다."}}