{"color": {"name": "purple", "url": "https://pokeapi.co/api/v2/pokemon-color/7/"}, "evolves_from_species": null, "generation": "sinnoh", "id": 484, "names": {"ja": "パルキア", "ko": "펄기아", "fr": "Palkia", "de": "Palkia", "es": "Palkia", "it": "Palkia", "en": "Palkia"}, "descriptions": {"en": "This Pokémon is feared as a deity in Hisuian legend. The birth of Palkia was what caused the walls of our world to disappear, creating a sky that spans for infinity.", "it": "Ha l’abilità di distorcere lo spazio. Nella mitologia della regione di Sinnoh è una divinità.", "es": "Tiene la habilidad de distorsionar el espacio. La mitología de Sinnoh lo describe como una deidad.", "de": "Es hat die Macht, den Raum zu krümmen. In den Mythen von Sinnoh erscheint es als Gottheit.", "fr": "Il peut modeler l’espace. Les mythes de Sinnoh en parlent comme d’une divinité ancienne.", "ko": "공간을 뒤틀리게 하는 능력을 가졌으며 신오지방의 신화에서는 신으로 묘사되고 있다.", "ja": "くうかんを　ゆがめる　のうりょくを もち　シンオウちほうの　しんわでは かみさまとして　えがかれている。"}}