{
	"color": { "name": "pink", "url": "https://pokeapi.co/api/v2/pokemon-color/6/" },
	"evolves_from_species": { "name": "feebas" },
	"generation": "hoenn",
	"id": 349,
	"names": {
		"ja": "ミロカロス",
		"ko": "밀로틱",
		"fr": "Milobellus",
		"de": "Milotic",
		"es": "Milotic",
		"it": "Milotic",
		"en": "Milotic"
	},
	"descriptions": {
		"en": "It’s said that a glimpse of a Milotic and its beauty will calm any hostile emotions you’re feeling.",
		"it": "Si dice che la sua bellezza sia in grado di alleviare qualsiasi dolore nel cuore di chi lo ammira.",
		"es": "Se dice que su hermosa figura puede apaciguar el corazón de aquellos que tengan el ánimo alterado.",
		"de": "Es heißt, der Anblick seiner wunderschönen Gestalt könne selbst das verrohteste Herz erweichen.",
		"fr": "On dit que la beauté de ce Pokémon est telle qu’elle apaise l’esprit de ceux qui le voient.",
		"ko": "밀로틱의 아름다운 모습을 본 자는 황폐해진 마음이 치유된다고 한다.",
		"ja": "ミロカロスの　うつくしい　すがたを みた　ものは　すさんだ　こころが いやされると　いわれている。"
	}
}
